<?xml version="1.0" encoding="UTF-8"?>
<list xmlns:xsi="http://www.w3.org/2001/XMLSchema-instance" xsi:noNamespaceSchemaLocation="../../../xsd/items.xsd">
	<item id="8100" type="EtcItem" nameRu="Разбитый Осколок Голема" nameEn="Destroyed Golem Shards">
		<set name="icon" val="icon.etc_debris_i00" />
		<set name="immediate_effect" val="1" />
		<set name="material" val="paper" />
		<set name="is_tradable" val="false" />
		<set name="is_dropable" val="false" />
		<set name="is_sellable" val="false" />
		<set name="is_depositable" val="false" />
		<set name="is_stackable" val="true" />
		<set name="is_questitem" val="true" />
	</item>
	<item id="8101" type="EtcItem" nameRu="Просьба Гномов" nameEn="Dwarf's Favor">
		<set name="icon" val="icon.etc_letter_white_i00" />
		<set name="immediate_effect" val="1" />
		<set name="material" val="paper" />
		<set name="is_tradable" val="false" />
		<set name="is_dropable" val="false" />
		<set name="is_sellable" val="false" />
		<set name="is_stackable" val="true" />
		<set name="is_questitem" val="true" />
	</item>
	<item id="8102" type="Weapon" nameRu="Меч Паагрио - Фокусировка" nameEn="Pa'agrian Sword - Focus">
		<set name="icon" val="icon.weapon_sword_of_paagrio_i01" />
		<set name="default_action" val="equip" />
		<set name="weapon_type" val="bigsword" />
		<set name="bodypart" val="lrhand" />
		<set name="random_damage" val="10" />
		<set name="attack_range" val="40" />
		<set name="damage_range" val="0;0;44;120" />
		<set name="immediate_effect" val="1" />
		<set name="crystal_count" val="1322" />
		<set name="crystal_type" val="c" />
		<set name="material" val="steel" />
		<set name="weight" val="1980" />
		<set name="price" val="3304300" />
		<set name="change_weaponId" val="9285" />
		<set name="soulshots" val="3" />
		<set name="spiritshots" val="3" />
		<set name="enchant_enabled" val="1" />
		<set name="item_skill" val="3010-3" />
		<for>
			<set order="0x08" stat="pAtk" val="169" />
			<set order="0x08" stat="mAtk" val="76" />
			<set order="0x08" stat="rCrit" val="8" />
			<set order="0x08" stat="pAtkSpd" val="325" />
			<enchant val="0" order="0x0C" stat="pAtk" />
			<enchant val="0" order="0x0C" stat="mAtk" />
		</for>
	</item>
	<item id="8103" type="Weapon" nameRu="Меч Паагрио - Здоровье" nameEn="Pa'agrian Sword - Health">
		<set name="icon" val="icon.weapon_sword_of_paagrio_i01" />
		<set name="default_action" val="equip" />
		<set name="weapon_type" val="bigsword" />
		<set name="bodypart" val="lrhand" />
		<set name="random_damage" val="10" />
		<set name="attack_range" val="40" />
		<set name="damage_range" val="0;0;44;120" />
		<set name="immediate_effect" val="1" />
		<set name="crystal_count" val="1322" />
		<set name="crystal_type" val="c" />
		<set name="material" val="steel" />
		<set name="weight" val="1980" />
		<set name="price" val="3304300" />
		<set name="change_weaponId" val="9286" />
		<set name="soulshots" val="3" />
		<set name="spiritshots" val="3" />
		<set name="enchant_enabled" val="1" />
		<set name="item_skill" val="3013-1" />
		<for>
			<set order="0x08" stat="pAtk" val="169" />
			<set order="0x08" stat="mAtk" val="76" />
			<set order="0x08" stat="rCrit" val="8" />
			<set order="0x08" stat="pAtkSpd" val="325" />
			<enchant val="0" order="0x0C" stat="pAtk" />
			<enchant val="0" order="0x0C" stat="mAtk" />
		</for>
	</item>
	<item id="8104" type="Weapon" nameRu="Меч Паагрио - Крит. Поглощение HP" nameEn="Pa'agrian Sword - Critical Drain">
		<set name="icon" val="icon.weapon_sword_of_paagrio_i01" />
		<set name="default_action" val="equip" />
		<set name="weapon_type" val="bigsword" />
		<set name="bodypart" val="lrhand" />
		<set name="random_damage" val="10" />
		<set name="attack_range" val="40" />
		<set name="damage_range" val="0;0;44;120" />
		<set name="immediate_effect" val="1" />
		<set name="crystal_count" val="1322" />
		<set name="crystal_type" val="c" />
		<set name="material" val="steel" />
		<set name="weight" val="1980" />
		<set name="price" val="3304300" />
		<set name="change_weaponId" val="9287" />
		<set name="soulshots" val="3" />
		<set name="spiritshots" val="3" />
		<set name="enchant_enabled" val="1" />
		<set name="oncrit_chance" val="35" />
		<set name="oncrit_skill" val="3022-3" />
		<for>
			<set order="0x08" stat="pAtk" val="169" />
			<set order="0x08" stat="mAtk" val="76" />
			<set order="0x08" stat="rCrit" val="8" />
			<set order="0x08" stat="pAtkSpd" val="325" />
			<enchant val="0" order="0x0C" stat="pAtk" />
			<enchant val="0" order="0x0C" stat="mAtk" />
		</for>
	</item>
	<item id="8105" type="Weapon" nameRu="Меч Стража - Крит. Поглощение HP" nameEn="Guardian Sword - Critical Drain">
		<set name="icon" val="icon.weapon_guardians_sword_i01" />
		<set name="default_action" val="equip" />
		<set name="weapon_type" val="bigsword" />
		<set name="bodypart" val="lrhand" />
		<set name="random_damage" val="10" />
		<set name="attack_range" val="40" />
		<set name="damage_range" val="0;0;44;120" />
		<set name="immediate_effect" val="1" />
		<set name="crystal_count" val="1346" />
		<set name="crystal_type" val="b" />
		<set name="material" val="steel" />
		<set name="weight" val="1930" />
		<set name="price" val="10091400" />
		<set name="change_weaponId" val="9321" />
		<set name="soulshots" val="1" />
		<set name="spiritshots" val="1" />
		<set name="enchant_enabled" val="1" />
		<set name="oncrit_chance" val="35" />
		<set name="oncrit_skill" val="3022-6" />
		<for>
			<set order="0x08" stat="pAtk" val="236" />
			<set order="0x08" stat="mAtk" val="99" />
			<set order="0x08" stat="rCrit" val="8" />
			<set order="0x08" stat="pAtkSpd" val="325" />
			<enchant val="0" order="0x0C" stat="pAtk" />
			<enchant val="0" order="0x0C" stat="mAtk" />
		</for>
	</item>
	<item id="8106" type="Weapon" nameRu="Меч Стража - Здоровье" nameEn="Guardian Sword - Health">
		<set name="icon" val="icon.weapon_guardians_sword_i01" />
		<set name="default_action" val="equip" />
		<set name="weapon_type" val="bigsword" />
		<set name="bodypart" val="lrhand" />
		<set name="random_damage" val="10" />
		<set name="attack_range" val="40" />
		<set name="damage_range" val="0;0;44;120" />
		<set name="immediate_effect" val="1" />
		<set name="crystal_count" val="1346" />
		<set name="crystal_type" val="b" />
		<set name="material" val="steel" />
		<set name="weight" val="1930" />
		<set name="price" val="10091400" />
		<set name="change_weaponId" val="9322" />
		<set name="soulshots" val="1" />
		<set name="spiritshots" val="1" />
		<set name="enchant_enabled" val="1" />
		<set name="item_skill" val="3013-1" />
		<for>
			<set order="0x08" stat="pAtk" val="236" />
			<set order="0x08" stat="mAtk" val="99" />
			<set order="0x08" stat="rCrit" val="8" />
			<set order="0x08" stat="pAtkSpd" val="325" />
			<enchant val="0" order="0x0C" stat="pAtk" />
			<enchant val="0" order="0x0C" stat="mAtk" />
		</for>
	</item>
	<item id="8107" type="Weapon" nameRu="Меч Стража - Крит. Кровопускание" nameEn="Guardian Sword - Critical Bleed">
		<set name="icon" val="icon.weapon_guardians_sword_i01" />
		<set name="default_action" val="equip" />
		<set name="weapon_type" val="bigsword" />
		<set name="bodypart" val="lrhand" />
		<set name="random_damage" val="10" />
		<set name="attack_range" val="40" />
		<set name="damage_range" val="0;0;44;120" />
		<set name="immediate_effect" val="1" />
		<set name="crystal_count" val="1346" />
		<set name="crystal_type" val="b" />
		<set name="material" val="steel" />
		<set name="weight" val="1930" />
		<set name="price" val="10091400" />
		<set name="change_weaponId" val="9323" />
		<set name="soulshots" val="1" />
		<set name="spiritshots" val="1" />
		<set name="enchant_enabled" val="1" />
		<set name="oncrit_chance" val="24" />
		<set name="oncrit_skill" val="3055-1" />
		<for>
			<set order="0x08" stat="pAtk" val="236" />
			<set order="0x08" stat="mAtk" val="99" />
			<set order="0x08" stat="rCrit" val="8" />
			<set order="0x08" stat="pAtkSpd" val="325" />
			<enchant val="0" order="0x0C" stat="pAtk" />
			<enchant val="0" order="0x0C" stat="mAtk" />
		</for>
	</item>
	<item id="8108" type="Weapon" nameRu="Мастер Инферно - Ускорение" nameEn="Infernal Master - Haste">
		<set name="icon" val="icon.weapon_inferno_master_i01" />
		<set name="default_action" val="equip" />
		<set name="weapon_type" val="bigsword" />
		<set name="bodypart" val="lrhand" />
		<set name="random_damage" val="10" />
		<set name="attack_range" val="40" />
		<set name="damage_range" val="0;0;46;120" />
		<set name="immediate_effect" val="1" />
		<set name="crystal_count" val="1128" />
		<set name="crystal_type" val="a" />
		<set name="material" val="fine_steel" />
		<set name="weight" val="1900" />
		<set name="price" val="14098000" />
		<set name="change_weaponId" val="9333" />
		<set name="soulshots" val="1" />
		<set name="spiritshots" val="1" />
		<set name="enchant_enabled" val="1" />
		<set name="item_skill" val="3068-2" />
		<for>
			<set order="0x08" stat="pAtk" val="259" />
			<set order="0x08" stat="mAtk" val="107" />
			<set order="0x08" stat="rCrit" val="8" />
			<set order="0x08" stat="pAtkSpd" val="325" />
			<enchant val="0" order="0x0C" stat="pAtk" />
			<enchant val="0" order="0x0C" stat="mAtk" />
		</for>
	</item>
	<item id="8109" type="Weapon" nameRu="Мастер Инферно - Крит. Урон" nameEn="Infernal Master - Critical Damage">
		<set name="icon" val="icon.weapon_inferno_master_i01" />
		<set name="default_action" val="equip" />
		<set name="weapon_type" val="bigsword" />
		<set name="bodypart" val="lrhand" />
		<set name="random_damage" val="10" />
		<set name="attack_range" val="40" />
		<set name="damage_range" val="0;0;46;120" />
		<set name="immediate_effect" val="1" />
		<set name="crystal_count" val="1128" />
		<set name="crystal_type" val="a" />
		<set name="material" val="fine_steel" />
		<set name="weight" val="1900" />
		<set name="price" val="14098000" />
		<set name="change_weaponId" val="9334" />
		<set name="soulshots" val="1" />
		<set name="spiritshots" val="1" />
		<set name="enchant_enabled" val="1" />
		<set name="item_skill" val="3067-1" />
		<for>
			<set order="0x08" stat="pAtk" val="259" />
			<set order="0x08" stat="mAtk" val="107" />
			<set order="0x08" stat="rCrit" val="8" />
			<set order="0x08" stat="pAtkSpd" val="325" />
			<enchant val="0" order="0x0C" stat="pAtk" />
			<enchant val="0" order="0x0C" stat="mAtk" />
		</for>
	</item>
	<item id="8110" type="Weapon" nameRu="Мастер Инферно - Фокусировка" nameEn="Infernal Master - Focus">
		<set name="icon" val="icon.weapon_inferno_master_i01" />
		<set name="default_action" val="equip" />
		<set name="weapon_type" val="bigsword" />
		<set name="bodypart" val="lrhand" />
		<set name="random_damage" val="10" />
		<set name="attack_range" val="40" />
		<set name="damage_range" val="0;0;46;120" />
		<set name="immediate_effect" val="1" />
		<set name="crystal_count" val="1128" />
		<set name="crystal_type" val="a" />
		<set name="material" val="fine_steel" />
		<set name="weight" val="1900" />
		<set name="price" val="14098000" />
		<set name="change_weaponId" val="9335" />
		<set name="soulshots" val="1" />
		<set name="spiritshots" val="1" />
		<set name="enchant_enabled" val="1" />
		<set name="item_skill" val="3050-1" />
		<for>
			<set order="0x08" stat="pAtk" val="259" />
			<set order="0x08" stat="mAtk" val="107" />
			<set order="0x08" stat="rCrit" val="8" />
			<set order="0x08" stat="pAtkSpd" val="325" />
			<enchant val="0" order="0x0C" stat="pAtk" />
			<enchant val="0" order="0x0C" stat="mAtk" />
		</for>
	</item>
	<item id="8111" type="Weapon" nameRu="Мистический Меч - Проницательность" nameEn="Mysterious Sword - Acumen">
		<set name="icon" val="icon.weapon_mystery_sword_i01" />
		<set name="default_action" val="equip" />
		<set name="weapon_type" val="sword" />
		<set name="bodypart" val="rhand" />
		<set name="random_damage" val="10" />
		<set name="attack_range" val="40" />
		<set name="damage_range" val="0;0;40;120" />
		<set name="immediate_effect" val="1" />
		<set name="crystal_count" val="705" />
		<set name="crystal_type" val="c" />
		<set name="material" val="fine_steel" />
		<set name="weight" val="1430" />
		<set name="price" val="1762900" />
		<set name="soulshots" val="2" />
		<set name="spiritshots" val="2" />
		<set name="enchant_enabled" val="1" />
		<set name="is_magic_weapon" val="true" />
		<set name="item_skill" val="3047-1" />
		<for>
			<set order="0x08" stat="pAtk" val="85" />
			<set order="0x08" stat="mAtk" val="81" />
			<set order="0x08" stat="rCrit" val="8" />
			<set order="0x08" stat="pAtkSpd" val="379" />
			<enchant val="0" order="0x0C" stat="pAtk" />
			<enchant val="0" order="0x0C" stat="mAtk" />
		</for>
	</item>
	<item id="8112" type="Weapon" nameRu="Мистический Меч - Маг. Сила" nameEn="Mysterious Sword - M. Atk.">
		<set name="icon" val="icon.weapon_mystery_sword_i01" />
		<set name="default_action" val="equip" />
		<set name="weapon_type" val="sword" />
		<set name="bodypart" val="rhand" />
		<set name="random_damage" val="10" />
		<set name="attack_range" val="40" />
		<set name="damage_range" val="0;0;40;120" />
		<set name="immediate_effect" val="1" />
		<set name="crystal_count" val="705" />
		<set name="crystal_type" val="c" />
		<set name="material" val="fine_steel" />
		<set name="weight" val="1430" />
		<set name="price" val="1762900" />
		<set name="soulshots" val="2" />
		<set name="spiritshots" val="2" />
		<set name="enchant_enabled" val="1" />
		<set name="is_magic_weapon" val="true" />
		<set name="item_skill" val="3077-1" />
		<for>
			<set order="0x08" stat="pAtk" val="85" />
			<set order="0x08" stat="mAtk" val="81" />
			<set order="0x08" stat="rCrit" val="8" />
			<set order="0x08" stat="pAtkSpd" val="379" />
			<enchant val="0" order="0x0C" stat="pAtk" />
			<enchant val="0" order="0x0C" stat="mAtk" />
		</for>
	</item>
	<item id="8113" type="Weapon" nameRu="Мистический Меч - Маг. Слабость" nameEn="Mysterious Sword - Magic Weakness">
		<set name="icon" val="icon.weapon_mystery_sword_i01" />
		<set name="default_action" val="equip" />
		<set name="weapon_type" val="sword" />
		<set name="bodypart" val="rhand" />
		<set name="random_damage" val="10" />
		<set name="attack_range" val="40" />
		<set name="damage_range" val="0;0;40;120" />
		<set name="immediate_effect" val="1" />
		<set name="crystal_count" val="705" />
		<set name="crystal_type" val="c" />
		<set name="material" val="fine_steel" />
		<set name="weight" val="1430" />
		<set name="price" val="1762900" />
		<set name="soulshots" val="2" />
		<set name="spiritshots" val="2" />
		<set name="enchant_enabled" val="1" />
		<set name="is_magic_weapon" val="true" />
		<set name="onmagic_chance" val="8" />
		<set name="onmagic_skill" val="1164-7" />
		<for>
			<set order="0x08" stat="pAtk" val="85" />
			<set order="0x08" stat="mAtk" val="81" />
			<set order="0x08" stat="rCrit" val="8" />
			<set order="0x08" stat="pAtkSpd" val="379" />
			<enchant val="0" order="0x0C" stat="pAtk" />
			<enchant val="0" order="0x0C" stat="mAtk" />
		</for>
	</item>
	<item id="8114" type="Weapon" nameRu="Меч Затмения - Воодушевление" nameEn="Ecliptic Sword - Empower">
		<set name="icon" val="icon.weapon_sword_of_eclipse_i01" />
		<set name="default_action" val="equip" />
		<set name="weapon_type" val="sword" />
		<set name="bodypart" val="rhand" />
		<set name="random_damage" val="10" />
		<set name="attack_range" val="40" />
		<set name="damage_range" val="0;0;40;120" />
		<set name="immediate_effect" val="1" />
		<set name="crystal_count" val="1885" />
		<set name="crystal_type" val="c" />
		<set name="material" val="oriharukon" />
		<set name="weight" val="1380" />
		<set name="price" val="4713500" />
		<set name="soulshots" val="3" />
		<set name="spiritshots" val="3" />
		<set name="enchant_enabled" val="1" />
		<set name="is_magic_weapon" val="true" />
		<set name="item_skill" val="3076-4" />
		<for>
			<set order="0x08" stat="pAtk" val="125" />
			<set order="0x08" stat="mAtk" val="111" />
			<set order="0x08" stat="rCrit" val="8" />
			<set order="0x08" stat="pAtkSpd" val="379" />
			<enchant val="0" order="0x0C" stat="pAtk" />
			<enchant val="0" order="0x0C" stat="mAtk" />
		</for>
	</item>
	<item id="8115" type="Weapon" nameRu="Меч Затмения - Маг. Сила" nameEn="Ecliptic Sword - M. Atk.">
		<set name="icon" val="icon.weapon_sword_of_eclipse_i01" />
		<set name="default_action" val="equip" />
		<set name="weapon_type" val="sword" />
		<set name="bodypart" val="rhand" />
		<set name="random_damage" val="10" />
		<set name="attack_range" val="40" />
		<set name="damage_range" val="0;0;40;120" />
		<set name="immediate_effect" val="1" />
		<set name="crystal_count" val="1885" />
		<set name="crystal_type" val="c" />
		<set name="material" val="oriharukon" />
		<set name="weight" val="1380" />
		<set name="price" val="4713500" />
		<set name="soulshots" val="3" />
		<set name="spiritshots" val="3" />
		<set name="enchant_enabled" val="1" />
		<set name="is_magic_weapon" val="true" />
		<set name="item_skill" val="3077-4" />
		<for>
			<set order="0x08" stat="pAtk" val="125" />
			<set order="0x08" stat="mAtk" val="111" />
			<set order="0x08" stat="rCrit" val="8" />
			<set order="0x08" stat="pAtkSpd" val="379" />
			<enchant val="0" order="0x0C" stat="pAtk" />
			<enchant val="0" order="0x0C" stat="mAtk" />
		</for>
	</item>
	<item id="8116" type="Weapon" nameRu="Меч Затмения - Безмолвие" nameEn="Ecliptic Sword - Magic Silence">
		<set name="icon" val="icon.weapon_sword_of_eclipse_i01" />
		<set name="default_action" val="equip" />
		<set name="weapon_type" val="sword" />
		<set name="bodypart" val="rhand" />
		<set name="random_damage" val="10" />
		<set name="attack_range" val="40" />
		<set name="damage_range" val="0;0;40;120" />
		<set name="immediate_effect" val="1" />
		<set name="crystal_count" val="1885" />
		<set name="crystal_type" val="c" />
		<set name="material" val="oriharukon" />
		<set name="weight" val="1380" />
		<set name="price" val="4713500" />
		<set name="soulshots" val="3" />
		<set name="spiritshots" val="3" />
		<set name="enchant_enabled" val="1" />
		<set name="is_magic_weapon" val="true" />
		<set name="onmagic_chance" val="10" />
		<set name="onmagic_skill" val="3078-4" />
		<for>
			<set order="0x08" stat="pAtk" val="125" />
			<set order="0x08" stat="mAtk" val="111" />
			<set order="0x08" stat="rCrit" val="8" />
			<set order="0x08" stat="pAtkSpd" val="379" />
			<enchant val="0" order="0x0C" stat="pAtk" />
			<enchant val="0" order="0x0C" stat="mAtk" />
		</for>
	</item>
	<item id="8117" type="Weapon" nameRu="Слезы Чародея - Проницательность" nameEn="Wizard's Tear - Acumen">
		<set name="icon" val="icon.weapon_tears_of_wizard_i01" />
		<set name="default_action" val="equip" />
		<set name="weapon_type" val="sword" />
		<set name="bodypart" val="rhand" />
		<set name="random_damage" val="10" />
		<set name="attack_range" val="40" />
		<set name="damage_range" val="0;0;40;120" />
		<set name="immediate_effect" val="1" />
		<set name="crystal_count" val="1346" />
		<set name="crystal_type" val="b" />
		<set name="material" val="oriharukon" />
		<set name="weight" val="1350" />
		<set name="price" val="10091400" />
		<set name="soulshots" val="1" />
		<set name="spiritshots" val="1" />
		<set name="enchant_enabled" val="1" />
		<set name="is_magic_weapon" val="true" />
		<set name="item_skill" val="3047-1" />
		<for>
			<set order="0x08" stat="pAtk" val="155" />
			<set order="0x08" stat="mAtk" val="132" />
			<set order="0x08" stat="rCrit" val="8" />
			<set order="0x08" stat="pAtkSpd" val="379" />
			<enchant val="0" order="0x0C" stat="pAtk" />
			<enchant val="0" order="0x0C" stat="mAtk" />
		</for>
	</item>
	<item id="8118" type="Weapon" nameRu="Слезы Чародея - Маг. Сила" nameEn="Wizard's Tear - M. Atk.">
		<set name="icon" val="icon.weapon_tears_of_wizard_i01" />
		<set name="default_action" val="equip" />
		<set name="weapon_type" val="sword" />
		<set name="bodypart" val="rhand" />
		<set name="random_damage" val="10" />
		<set name="attack_range" val="40" />
		<set name="damage_range" val="0;0;40;120" />
		<set name="immediate_effect" val="1" />
		<set name="crystal_count" val="1346" />
		<set name="crystal_type" val="b" />
		<set name="material" val="oriharukon" />
		<set name="weight" val="1350" />
		<set name="price" val="10091400" />
		<set name="soulshots" val="1" />
		<set name="spiritshots" val="1" />
		<set name="enchant_enabled" val="1" />
		<set name="is_magic_weapon" val="true" />
		<set name="item_skill" val="3077-6" />
		<for>
			<set order="0x08" stat="pAtk" val="155" />
			<set order="0x08" stat="mAtk" val="132" />
			<set order="0x08" stat="rCrit" val="8" />
			<set order="0x08" stat="pAtkSpd" val="379" />
			<enchant val="0" order="0x0C" stat="pAtk" />
			<enchant val="0" order="0x0C" stat="mAtk" />
		</for>
	</item>
	<item id="8119" type="Weapon" nameRu="Слезы Чародея - Конверсия" nameEn="Wizard's Tear - Conversion">
		<set name="icon" val="icon.weapon_tears_of_wizard_i01" />
		<set name="default_action" val="equip" />
		<set name="weapon_type" val="sword" />
		<set name="bodypart" val="rhand" />
		<set name="random_damage" val="10" />
		<set name="attack_range" val="40" />
		<set name="damage_range" val="0;0;40;120" />
		<set name="immediate_effect" val="1" />
		<set name="crystal_count" val="1346" />
		<set name="crystal_type" val="b" />
		<set name="material" val="oriharukon" />
		<set name="weight" val="1350" />
		<set name="price" val="10091400" />
		<set name="soulshots" val="1" />
		<set name="spiritshots" val="1" />
		<set name="enchant_enabled" val="1" />
		<set name="is_magic_weapon" val="true" />
		<set name="item_skill" val="3048-1" />
		<for>
			<set order="0x08" stat="pAtk" val="155" />
			<set order="0x08" stat="mAtk" val="132" />
			<set order="0x08" stat="rCrit" val="8" />
			<set order="0x08" stat="pAtkSpd" val="379" />
			<enchant val="0" order="0x0C" stat="pAtk" />
			<enchant val="0" order="0x0C" stat="mAtk" />
		</for>
	</item>
	<item id="8120" type="Weapon" nameRu="Молот Гномов - Здоровье" nameEn="Dwarven Hammer - Health">
		<set name="icon" val="icon.weapon_dwarven_hammer_i01" />
		<set name="default_action" val="equip" />
		<set name="weapon_type" val="bigblunt" />
		<set name="bodypart" val="lrhand" />
		<set name="random_damage" val="20" />
		<set name="attack_range" val="40" />
		<set name="damage_range" val="0;0;44;120" />
		<set name="immediate_effect" val="1" />
		<set name="crystal_count" val="1885" />
		<set name="crystal_type" val="c" />
		<set name="material" val="steel" />
		<set name="weight" val="2010" />
		<set name="price" val="4713500" />
		<set name="soulshots" val="3" />
		<set name="spiritshots" val="3" />
		<set name="enchant_enabled" val="1" />
		<set name="item_skill" val="3013-1" />
		<for>
			<set order="0x08" stat="pAtk" val="190" />
			<set order="0x08" stat="mAtk" val="83" />
			<set order="0x08" stat="rCrit" val="4" />
			<add order="0x10" stat="accCombat" val="4.75" />
			<set order="0x08" stat="pAtkSpd" val="325" />
			<enchant val="0" order="0x0C" stat="pAtk" />
			<enchant val="0" order="0x0C" stat="mAtk" />
		</for>
	</item>
	<item id="8121" type="Weapon" nameRu="Молот Гномов - Ярость" nameEn="Dwarven Hammer - Anger">
		<set name="icon" val="icon.weapon_dwarven_hammer_i01" />
		<set name="default_action" val="equip" />
		<set name="weapon_type" val="bigblunt" />
		<set name="bodypart" val="lrhand" />
		<set name="random_damage" val="20" />
		<set name="attack_range" val="40" />
		<set name="damage_range" val="0;0;44;120" />
		<set name="immediate_effect" val="1" />
		<set name="crystal_count" val="1885" />
		<set name="crystal_type" val="c" />
		<set name="material" val="steel" />
		<set name="weight" val="2010" />
		<set name="price" val="4713500" />
		<set name="soulshots" val="3" />
		<set name="spiritshots" val="3" />
		<set name="enchant_enabled" val="1" />
		<set name="item_skill" val="3012-4" />
		<for>
			<set order="0x08" stat="pAtk" val="190" />
			<set order="0x08" stat="mAtk" val="83" />
			<set order="0x08" stat="rCrit" val="4" />
			<add order="0x10" stat="accCombat" val="4.75" />
			<set order="0x08" stat="pAtkSpd" val="325" />
			<enchant val="0" order="0x0C" stat="pAtk" />
			<enchant val="0" order="0x0C" stat="mAtk" />
		</for>
	</item>
	<item id="8122" type="Weapon" nameRu="Молот Гномов - Крит. Кровопускание" nameEn="Dwarven Hammer - Critical Bleed">
		<set name="icon" val="icon.weapon_dwarven_hammer_i01" />
		<set name="default_action" val="equip" />
		<set name="weapon_type" val="bigblunt" />
		<set name="bodypart" val="lrhand" />
		<set name="random_damage" val="20" />
		<set name="attack_range" val="40" />
		<set name="damage_range" val="0;0;44;120" />
		<set name="immediate_effect" val="1" />
		<set name="crystal_count" val="1885" />
		<set name="crystal_type" val="c" />
		<set name="material" val="steel" />
		<set name="weight" val="2010" />
		<set name="price" val="4713500" />
		<set name="soulshots" val="3" />
		<set name="spiritshots" val="3" />
		<set name="enchant_enabled" val="1" />
		<set name="oncrit_chance" val="42" />
		<set name="oncrit_skill" val="3021-4" />
		<for>
			<set order="0x08" stat="pAtk" val="190" />
			<set order="0x08" stat="mAtk" val="83" />
			<set order="0x08" stat="rCrit" val="4" />
			<add order="0x10" stat="accCombat" val="4.75" />
			<set order="0x08" stat="pAtkSpd" val="325" />
			<enchant val="0" order="0x0C" stat="pAtk" />
			<enchant val="0" order="0x0C" stat="mAtk" />
		</for>
	</item>
	<item id="8123" type="Weapon" nameRu="Рог Карика - Фокусировка" nameEn="Karik Horn - Focus">
		<set name="icon" val="icon.weapon_horn_of_karik_i01" />
		<set name="default_action" val="equip" />
		<set name="weapon_type" val="bigblunt" />
		<set name="bodypart" val="lrhand" />
		<set name="random_damage" val="20" />
		<set name="attack_range" val="40" />
		<set name="damage_range" val="0;0;44;120" />
		<set name="immediate_effect" val="1" />
		<set name="crystal_count" val="1322" />
		<set name="crystal_type" val="c" />
		<set name="material" val="oriharukon" />
		<set name="weight" val="2020" />
		<set name="price" val="3304300" />
		<set name="soulshots" val="3" />
		<set name="spiritshots" val="3" />
		<set name="enchant_enabled" val="1" />
		<set name="item_skill" val="3010-3" />
		<for>
			<set order="0x08" stat="pAtk" val="169" />
			<set order="0x08" stat="mAtk" val="76" />
			<set order="0x08" stat="rCrit" val="4" />
			<add order="0x10" stat="accCombat" val="4.75" />
			<set order="0x08" stat="pAtkSpd" val="325" />
			<enchant val="0" order="0x0C" stat="pAtk" />
			<enchant val="0" order="0x0C" stat="mAtk" />
		</for>
	</item>
	<item id="8124" type="Weapon" nameRu="Рог Карика - Ускорение" nameEn="Karik Horn - Haste">
		<set name="icon" val="icon.weapon_horn_of_karik_i01" />
		<set name="default_action" val="equip" />
		<set name="weapon_type" val="bigblunt" />
		<set name="bodypart" val="lrhand" />
		<set name="random_damage" val="20" />
		<set name="attack_range" val="40" />
		<set name="damage_range" val="0;0;44;120" />
		<set name="immediate_effect" val="1" />
		<set name="crystal_count" val="1322" />
		<set name="crystal_type" val="c" />
		<set name="material" val="oriharukon" />
		<set name="weight" val="2020" />
		<set name="price" val="3304300" />
		<set name="soulshots" val="3" />
		<set name="spiritshots" val="3" />
		<set name="enchant_enabled" val="1" />
		<set name="item_skill" val="3036-3" />
		<for>
			<set order="0x08" stat="pAtk" val="169" />
			<set order="0x08" stat="mAtk" val="76" />
			<set order="0x08" stat="rCrit" val="4" />
			<add order="0x10" stat="accCombat" val="4.75" />
			<set order="0x08" stat="pAtkSpd" val="325" />
			<enchant val="0" order="0x0C" stat="pAtk" />
			<enchant val="0" order="0x0C" stat="mAtk" />
		</for>
	</item>
	<item id="8125" type="Weapon" nameRu="Рог Карика - Крит. Поглощение HP" nameEn="Karik Horn - Critical Drain">
		<set name="icon" val="icon.weapon_horn_of_karik_i01" />
		<set name="default_action" val="equip" />
		<set name="weapon_type" val="bigblunt" />
		<set name="bodypart" val="lrhand" />
		<set name="random_damage" val="20" />
		<set name="attack_range" val="40" />
		<set name="damage_range" val="0;0;44;120" />
		<set name="immediate_effect" val="1" />
		<set name="crystal_count" val="1322" />
		<set name="crystal_type" val="c" />
		<set name="material" val="oriharukon" />
		<set name="weight" val="2020" />
		<set name="price" val="3304300" />
		<set name="soulshots" val="3" />
		<set name="spiritshots" val="3" />
		<set name="enchant_enabled" val="1" />
		<set name="oncrit_chance" val="10" />
		<set name="oncrit_skill" val="3039-3" />
		<for>
			<set order="0x08" stat="pAtk" val="169" />
			<set order="0x08" stat="mAtk" val="76" />
			<set order="0x08" stat="rCrit" val="4" />
			<add order="0x10" stat="accCombat" val="4.75" />
			<set order="0x08" stat="pAtkSpd" val="325" />
			<enchant val="0" order="0x0C" stat="pAtk" />
			<enchant val="0" order="0x0C" stat="mAtk" />
		</for>
	</item>
	<item id="8126" type="Weapon" nameRu="Молот Разрушителя - Здоровье" nameEn="Destroyer Hammer - Health">
		<set name="icon" val="icon.weapon_hammer_of_destroyer_i01" />
		<set name="default_action" val="equip" />
		<set name="weapon_type" val="bigblunt" />
		<set name="bodypart" val="lrhand" />
		<set name="random_damage" val="20" />
		<set name="attack_range" val="40" />
		<set name="damage_range" val="0;0;44;120" />
		<set name="immediate_effect" val="1" />
		<set name="crystal_count" val="1128" />
		<set name="crystal_type" val="a" />
		<set name="material" val="fine_steel" />
		<set name="weight" val="1910" />
		<set name="price" val="14098000" />
		<set name="soulshots" val="1" />
		<set name="spiritshots" val="1" />
		<set name="enchant_enabled" val="1" />
		<set name="item_skill" val="3013-3" />
		<for>
			<set order="0x08" stat="pAtk" val="259" />
			<set order="0x08" stat="mAtk" val="107" />
			<set order="0x08" stat="rCrit" val="4" />
			<add order="0x10" stat="accCombat" val="4.75" />
			<set order="0x08" stat="pAtkSpd" val="325" />
			<enchant val="0" order="0x0C" stat="pAtk" />
			<enchant val="0" order="0x0C" stat="mAtk" />
		</for>
	</item>
	<item id="8127" type="Weapon" nameRu="Молот Разрушителя - Ускорение" nameEn="Destroyer Hammer - Haste">
		<set name="icon" val="icon.weapon_hammer_of_destroyer_i01" />
		<set name="default_action" val="equip" />
		<set name="weapon_type" val="bigblunt" />
		<set name="bodypart" val="lrhand" />
		<set name="random_damage" val="20" />
		<set name="attack_range" val="40" />
		<set name="damage_range" val="0;0;44;120" />
		<set name="immediate_effect" val="1" />
		<set name="crystal_count" val="1128" />
		<set name="crystal_type" val="a" />
		<set name="material" val="fine_steel" />
		<set name="weight" val="1910" />
		<set name="price" val="14098000" />
		<set name="soulshots" val="1" />
		<set name="spiritshots" val="1" />
		<set name="enchant_enabled" val="1" />
		<set name="item_skill" val="3068-2" />
		<for>
			<set order="0x08" stat="pAtk" val="259" />
			<set order="0x08" stat="mAtk" val="107" />
			<set order="0x08" stat="rCrit" val="4" />
			<add order="0x10" stat="accCombat" val="4.75" />
			<set order="0x08" stat="pAtkSpd" val="325" />
			<enchant val="0" order="0x0C" stat="pAtk" />
			<enchant val="0" order="0x0C" stat="mAtk" />
		</for>
	</item>
	<item id="8128" type="Weapon" nameRu="Молот Разрушителя - Крит. Поглощение HP" nameEn="Destroyer Hammer - Critical Drain">
		<set name="icon" val="icon.weapon_hammer_of_destroyer_i01" />
		<set name="default_action" val="equip" />
		<set name="weapon_type" val="bigblunt" />
		<set name="bodypart" val="lrhand" />
		<set name="random_damage" val="20" />
		<set name="attack_range" val="40" />
		<set name="damage_range" val="0;0;44;120" />
		<set name="immediate_effect" val="1" />
		<set name="crystal_count" val="1128" />
		<set name="crystal_type" val="a" />
		<set name="material" val="fine_steel" />
		<set name="weight" val="1910" />
		<set name="price" val="14098000" />
		<set name="soulshots" val="1" />
		<set name="spiritshots" val="1" />
		<set name="enchant_enabled" val="1" />
		<set name="oncrit_chance" val="24" />
		<set name="oncrit_skill" val="3059-1" />
		<set name="item_skill" val="3552-1" />
		<for>
			<set order="0x08" stat="pAtk" val="259" />
			<set order="0x08" stat="mAtk" val="107" />
			<set order="0x08" stat="rCrit" val="4" />
			<add order="0x10" stat="accCombat" val="4.75" />
			<set order="0x08" stat="pAtkSpd" val="325" />
			<enchant val="0" order="0x0C" stat="pAtk" />
			<enchant val="0" order="0x0C" stat="mAtk" />
		</for>
	</item>
	<item id="8129" type="Weapon" nameRu="Молот Ледяной Бури - Фокусировка" nameEn="Ice Storm Hammer - Focus">
		<set name="icon" val="icon.weapon_ice_storm_hammer_i01" />
		<set name="default_action" val="equip" />
		<set name="weapon_type" val="bigblunt" />
		<set name="bodypart" val="lrhand" />
		<set name="random_damage" val="20" />
		<set name="attack_range" val="40" />
		<set name="damage_range" val="0;0;44;120" />
		<set name="immediate_effect" val="1" />
		<set name="crystal_count" val="891" />
		<set name="crystal_type" val="b" />
		<set name="material" val="fine_steel" />
		<set name="weight" val="1950" />
		<set name="price" val="6680500" />
		<set name="soulshots" val="1" />
		<set name="spiritshots" val="1" />
		<set name="enchant_enabled" val="1" />
		<set name="item_skill" val="3010-5" />
		<for>
			<set order="0x08" stat="pAtk" val="213" />
			<set order="0x08" stat="mAtk" val="91" />
			<set order="0x08" stat="rCrit" val="4" />
			<add order="0x10" stat="accCombat" val="4.75" />
			<set order="0x08" stat="pAtkSpd" val="325" />
			<enchant val="0" order="0x0C" stat="pAtk" />
			<enchant val="0" order="0x0C" stat="mAtk" />
		</for>
	</item>
	<item id="8130" type="Weapon" nameRu="Молот Ледяной Бури - Ярость" nameEn="Ice Storm Hammer - Anger">
		<set name="icon" val="icon.weapon_ice_storm_hammer_i01" />
		<set name="default_action" val="equip" />
		<set name="weapon_type" val="bigblunt" />
		<set name="bodypart" val="lrhand" />
		<set name="random_damage" val="20" />
		<set name="attack_range" val="40" />
		<set name="damage_range" val="0;0;44;120" />
		<set name="immediate_effect" val="1" />
		<set name="crystal_count" val="891" />
		<set name="crystal_type" val="b" />
		<set name="material" val="fine_steel" />
		<set name="weight" val="1950" />
		<set name="price" val="6680500" />
		<set name="soulshots" val="1" />
		<set name="spiritshots" val="1" />
		<set name="enchant_enabled" val="1" />
		<set name="item_skill" val="3012-5" />
		<for>
			<set order="0x08" stat="pAtk" val="213" />
			<set order="0x08" stat="mAtk" val="91" />
			<set order="0x08" stat="rCrit" val="4" />
			<add order="0x10" stat="accCombat" val="4.75" />
			<set order="0x08" stat="pAtkSpd" val="325" />
			<enchant val="0" order="0x0C" stat="pAtk" />
			<enchant val="0" order="0x0C" stat="mAtk" />
		</for>
	</item>
	<item id="8131" type="Weapon" nameRu="Молот Ледяной Бури - Крит. Кровопускание" nameEn="Ice Storm Hammer - Critical Bleed">
		<set name="icon" val="icon.weapon_ice_storm_hammer_i01" />
		<set name="default_action" val="equip" />
		<set name="weapon_type" val="bigblunt" />
		<set name="bodypart" val="lrhand" />
		<set name="random_damage" val="20" />
		<set name="attack_range" val="40" />
		<set name="damage_range" val="0;0;44;120" />
		<set name="immediate_effect" val="1" />
		<set name="crystal_count" val="891" />
		<set name="crystal_type" val="b" />
		<set name="material" val="fine_steel" />
		<set name="weight" val="1950" />
		<set name="price" val="6680500" />
		<set name="soulshots" val="1" />
		<set name="spiritshots" val="1" />
		<set name="enchant_enabled" val="1" />
		<set name="oncrit_chance" val="41" />
		<set name="oncrit_skill" val="3021-5" />
		<for>
			<set order="0x08" stat="pAtk" val="213" />
			<set order="0x08" stat="mAtk" val="91" />
			<set order="0x08" stat="rCrit" val="4" />
			<add order="0x10" stat="accCombat" val="4.75" />
			<set order="0x08" stat="pAtkSpd" val="325" />
			<enchant val="0" order="0x0C" stat="pAtk" />
			<enchant val="0" order="0x0C" stat="mAtk" />
		</for>
	</item>
	<item id="8132" type="Weapon" nameRu="Звезда Боли - Здоровье" nameEn="Star Buster - Health">
		<set name="icon" val="icon.weapon_star_buster_i01" />
		<set name="default_action" val="equip" />
		<set name="weapon_type" val="bigblunt" />
		<set name="bodypart" val="lrhand" />
		<set name="random_damage" val="20" />
		<set name="attack_range" val="40" />
		<set name="damage_range" val="0;0;44;120" />
		<set name="immediate_effect" val="1" />
		<set name="crystal_count" val="1346" />
		<set name="crystal_type" val="b" />
		<set name="material" val="fine_steel" />
		<set name="weight" val="1930" />
		<set name="price" val="10091400" />
		<set name="soulshots" val="1" />
		<set name="spiritshots" val="1" />
		<set name="enchant_enabled" val="1" />
		<set name="item_skill" val="3013-1" />
		<for>
			<set order="0x08" stat="pAtk" val="236" />
			<set order="0x08" stat="mAtk" val="99" />
			<set order="0x08" stat="rCrit" val="4" />
			<add order="0x10" stat="accCombat" val="4.75" />
			<set order="0x08" stat="pAtkSpd" val="325" />
			<enchant val="0" order="0x0C" stat="pAtk" />
			<enchant val="0" order="0x0C" stat="mAtk" />
		</for>
	</item>
	<item id="8133" type="Weapon" nameRu="Звезда Боли - Ускорение" nameEn="Star Buster - Haste">
		<set name="icon" val="icon.weapon_star_buster_i01" />
		<set name="default_action" val="equip" />
		<set name="weapon_type" val="bigblunt" />
		<set name="bodypart" val="lrhand" />
		<set name="random_damage" val="20" />
		<set name="attack_range" val="40" />
		<set name="damage_range" val="0;0;44;120" />
		<set name="immediate_effect" val="1" />
		<set name="crystal_count" val="1346" />
		<set name="crystal_type" val="b" />
		<set name="material" val="fine_steel" />
		<set name="weight" val="1930" />
		<set name="price" val="10091400" />
		<set name="soulshots" val="1" />
		<set name="spiritshots" val="1" />
		<set name="enchant_enabled" val="1" />
		<set name="item_skill" val="3036-6" />
		<for>
			<set order="0x08" stat="pAtk" val="236" />
			<set order="0x08" stat="mAtk" val="99" />
			<set order="0x08" stat="rCrit" val="4" />
			<add order="0x10" stat="accCombat" val="4.75" />
			<set order="0x08" stat="pAtkSpd" val="325" />
			<enchant val="0" order="0x0C" stat="pAtk" />
			<enchant val="0" order="0x0C" stat="mAtk" />
		</for>
	</item>
	<item id="8134" type="Weapon" nameRu="Звезда Боли - Риск. Фокусировка" nameEn="Star Buster - Rsk. Focus">
		<set name="icon" val="icon.weapon_star_buster_i01" />
		<set name="default_action" val="equip" />
		<set name="weapon_type" val="bigblunt" />
		<set name="bodypart" val="lrhand" />
		<set name="random_damage" val="20" />
		<set name="attack_range" val="40" />
		<set name="damage_range" val="0;0;44;120" />
		<set name="immediate_effect" val="1" />
		<set name="crystal_count" val="1346" />
		<set name="crystal_type" val="b" />
		<set name="material" val="fine_steel" />
		<set name="weight" val="1930" />
		<set name="price" val="10091400" />
		<set name="soulshots" val="1" />
		<set name="spiritshots" val="1" />
		<set name="enchant_enabled" val="1" />
		<set name="item_skill" val="3027-6" />
		<for>
			<set order="0x08" stat="pAtk" val="236" />
			<set order="0x08" stat="mAtk" val="99" />
			<set order="0x08" stat="rCrit" val="4" />
			<add order="0x10" stat="accCombat" val="4.75" />
			<set order="0x08" stat="pAtkSpd" val="325" />
			<enchant val="0" order="0x0C" stat="pAtk" />
			<enchant val="0" order="0x0C" stat="mAtk" />
		</for>
	</item>
	<item id="8135" type="Weapon" nameRu="Крушитель Рока - Здоровье" nameEn="Doom Crusher - Health">
		<set name="icon" val="icon.weapon_doom_crusher_i01" />
		<set name="default_action" val="equip" />
		<set name="weapon_type" val="bigblunt" />
		<set name="bodypart" val="lrhand" />
		<set name="random_damage" val="20" />
		<set name="attack_range" val="40" />
		<set name="damage_range" val="0;0;44;120" />
		<set name="immediate_effect" val="1" />
		<set name="crystal_count" val="1659" />
		<set name="crystal_type" val="a" />
		<set name="material" val="fine_steel" />
		<set name="weight" val="1900" />
		<set name="price" val="20741000" />
		<set name="soulshots" val="1" />
		<set name="spiritshots" val="1" />
		<set name="enchant_enabled" val="1" />
		<set name="item_skill" val="3013-3" />
		<for>
			<set order="0x08" stat="pAtk" val="282" />
			<set order="0x08" stat="mAtk" val="114" />
			<set order="0x08" stat="rCrit" val="4" />
			<add order="0x10" stat="accCombat" val="4.75" />
			<set order="0x08" stat="pAtkSpd" val="325" />
			<enchant val="0" order="0x0C" stat="pAtk" />
			<enchant val="0" order="0x0C" stat="mAtk" />
		</for>
	</item>
	<item id="8136" type="Weapon" nameRu="Крушитель Рока - Ярость" nameEn="Doom Crusher - Anger">
		<set name="icon" val="icon.weapon_doom_crusher_i01" />
		<set name="default_action" val="equip" />
		<set name="weapon_type" val="bigblunt" />
		<set name="bodypart" val="lrhand" />
		<set name="random_damage" val="20" />
		<set name="attack_range" val="40" />
		<set name="damage_range" val="0;0;44;120" />
		<set name="immediate_effect" val="1" />
		<set name="crystal_count" val="1659" />
		<set name="crystal_type" val="a" />
		<set name="material" val="fine_steel" />
		<set name="weight" val="1900" />
		<set name="price" val="20741000" />
		<set name="soulshots" val="1" />
		<set name="spiritshots" val="1" />
		<set name="enchant_enabled" val="1" />
		<set name="item_skill" val="3057-2" />
		<for>
			<set order="0x08" stat="pAtk" val="282" />
			<set order="0x08" stat="mAtk" val="114" />
			<set order="0x08" stat="rCrit" val="4" />
			<add order="0x10" stat="accCombat" val="4.75" />
			<set order="0x08" stat="pAtkSpd" val="325" />
			<enchant val="0" order="0x0C" stat="pAtk" />
			<enchant val="0" order="0x0C" stat="mAtk" />
		</for>
	</item>
	<item id="8137" type="Weapon" nameRu="Крушитель Рока - Риск. Ускорение" nameEn="Doom Crusher - Rsk. Haste">
		<set name="icon" val="icon.weapon_doom_crusher_i01" />
		<set name="default_action" val="equip" />
		<set name="weapon_type" val="bigblunt" />
		<set name="bodypart" val="lrhand" />
		<set name="random_damage" val="20" />
		<set name="attack_range" val="40" />
		<set name="damage_range" val="0;0;44;120" />
		<set name="immediate_effect" val="1" />
		<set name="crystal_count" val="1659" />
		<set name="crystal_type" val="a" />
		<set name="material" val="fine_steel" />
		<set name="weight" val="1900" />
		<set name="price" val="20741000" />
		<set name="soulshots" val="1" />
		<set name="spiritshots" val="1" />
		<set name="enchant_enabled" val="1" />
		<set name="item_skill" val="3056-2" />
		<for>
			<set order="0x08" stat="pAtk" val="282" />
			<set order="0x08" stat="mAtk" val="114" />
			<set order="0x08" stat="rCrit" val="4" />
			<add order="0x10" stat="accCombat" val="4.75" />
			<set order="0x08" stat="pAtkSpd" val="325" />
			<enchant val="0" order="0x0C" stat="pAtk" />
			<enchant val="0" order="0x0C" stat="mAtk" />
		</for>
	</item>
	<item id="8138" type="Weapon" nameRu="Топор Затмения - Конверсия" nameEn="Ecliptic Axe - Conversion">
		<set name="icon" val="icon.weapon_eclipse_axe_i01" />
		<set name="default_action" val="equip" />
		<set name="weapon_type" val="blunt" />
		<set name="bodypart" val="rhand" />
		<set name="random_damage" val="20" />
		<set name="attack_range" val="40" />
		<set name="damage_range" val="0;0;40;120" />
		<set name="immediate_effect" val="1" />
		<set name="crystal_count" val="1885" />
		<set name="crystal_type" val="c" />
		<set name="material" val="fine_steel" />
		<set name="weight" val="1640" />
		<set name="price" val="4713500" />
		<set name="soulshots" val="3" />
		<set name="spiritshots" val="3" />
		<set name="enchant_enabled" val="1" />
		<set name="is_magic_weapon" val="true" />
		<set name="item_skill" val="3048-1" />
		<for>
			<set order="0x08" stat="pAtk" val="125" />
			<set order="0x08" stat="mAtk" val="111" />
			<set order="0x08" stat="rCrit" val="4" />
			<add order="0x10" stat="accCombat" val="4.75" />
			<set order="0x08" stat="pAtkSpd" val="379" />
			<enchant val="0" order="0x0C" stat="pAtk" />
			<enchant val="0" order="0x0C" stat="mAtk" />
		</for>
	</item>
	<item id="8139" type="Weapon" nameRu="Топор Затмения - Маг. Сила" nameEn="Ecliptic Axe - M. Atk.">
		<set name="icon" val="icon.weapon_eclipse_axe_i01" />
		<set name="default_action" val="equip" />
		<set name="weapon_type" val="blunt" />
		<set name="bodypart" val="rhand" />
		<set name="random_damage" val="20" />
		<set name="attack_range" val="40" />
		<set name="damage_range" val="0;0;40;120" />
		<set name="immediate_effect" val="1" />
		<set name="crystal_count" val="1885" />
		<set name="crystal_type" val="c" />
		<set name="material" val="fine_steel" />
		<set name="weight" val="1640" />
		<set name="price" val="4713500" />
		<set name="soulshots" val="3" />
		<set name="spiritshots" val="3" />
		<set name="enchant_enabled" val="1" />
		<set name="is_magic_weapon" val="true" />
		<set name="item_skill" val="3077-4" />
		<for>
			<set order="0x08" stat="pAtk" val="125" />
			<set order="0x08" stat="mAtk" val="111" />
			<set order="0x08" stat="rCrit" val="4" />
			<add order="0x10" stat="accCombat" val="4.75" />
			<set order="0x08" stat="pAtkSpd" val="379" />
			<enchant val="0" order="0x0C" stat="pAtk" />
			<enchant val="0" order="0x0C" stat="mAtk" />
		</for>
	</item>
	<item id="8140" type="Weapon" nameRu="Топор Затмения - Магические Оковы" nameEn="Ecliptic Axe - Magic Hold">
		<set name="icon" val="icon.weapon_eclipse_axe_i01" />
		<set name="default_action" val="equip" />
		<set name="weapon_type" val="blunt" />
		<set name="bodypart" val="rhand" />
		<set name="random_damage" val="20" />
		<set name="attack_range" val="40" />
		<set name="damage_range" val="0;0;40;120" />
		<set name="immediate_effect" val="1" />
		<set name="crystal_count" val="1885" />
		<set name="crystal_type" val="c" />
		<set name="material" val="fine_steel" />
		<set name="weight" val="1640" />
		<set name="price" val="4713500" />
		<set name="soulshots" val="3" />
		<set name="spiritshots" val="3" />
		<set name="enchant_enabled" val="1" />
		<set name="is_magic_weapon" val="true" />
		<set name="onmagic_chance" val="10" />
		<set name="onmagic_skill" val="1201-23" />
		<for>
			<set order="0x08" stat="pAtk" val="125" />
			<set order="0x08" stat="mAtk" val="111" />
			<set order="0x08" stat="rCrit" val="4" />
			<add order="0x10" stat="accCombat" val="4.75" />
			<set order="0x08" stat="pAtkSpd" val="379" />
			<enchant val="0" order="0x0C" stat="pAtk" />
			<enchant val="0" order="0x0C" stat="mAtk" />
		</for>
	</item>
	<item id="8141" type="Weapon" nameRu="Рассеиватель Заклинаний - Проницательность" nameEn="Spell Breaker - Acumen">
		<set name="icon" val="icon.weapon_spell_breaker_i01" />
		<set name="default_action" val="equip" />
		<set name="weapon_type" val="blunt" />
		<set name="bodypart" val="rhand" />
		<set name="random_damage" val="20" />
		<set name="attack_range" val="40" />
		<set name="damage_range" val="0;0;40;120" />
		<set name="immediate_effect" val="1" />
		<set name="crystal_count" val="891" />
		<set name="crystal_type" val="b" />
		<set name="material" val="fine_steel" />
		<set name="weight" val="1620" />
		<set name="price" val="6680500" />
		<set name="soulshots" val="1" />
		<set name="spiritshots" val="1" />
		<set name="enchant_enabled" val="1" />
		<set name="is_magic_weapon" val="true" />
		<set name="item_skill" val="3047-1" />
		<for>
			<set order="0x08" stat="pAtk" val="140" />
			<set order="0x08" stat="mAtk" val="122" />
			<set order="0x08" stat="rCrit" val="4" />
			<add order="0x10" stat="accCombat" val="4.75" />
			<set order="0x08" stat="pAtkSpd" val="379" />
			<enchant val="0" order="0x0C" stat="pAtk" />
			<enchant val="0" order="0x0C" stat="mAtk" />
		</for>
	</item>
	<item id="8142" type="Weapon" nameRu="Рассеиватель Заклинаний - Ментальный Щит" nameEn="Spell Breaker - Mental Shield">
		<set name="icon" val="icon.weapon_spell_breaker_i01" />
		<set name="default_action" val="equip" />
		<set name="weapon_type" val="blunt" />
		<set name="bodypart" val="rhand" />
		<set name="random_damage" val="20" />
		<set name="attack_range" val="40" />
		<set name="damage_range" val="0;0;40;120" />
		<set name="immediate_effect" val="1" />
		<set name="crystal_count" val="891" />
		<set name="crystal_type" val="b" />
		<set name="material" val="fine_steel" />
		<set name="weight" val="1620" />
		<set name="price" val="6680500" />
		<set name="soulshots" val="1" />
		<set name="spiritshots" val="1" />
		<set name="enchant_enabled" val="1" />
		<set name="is_magic_weapon" val="true" />
		<set name="onmagic_chance" val="50" />
		<set name="onmagic_skill" val="1035-4" />
		<for>
			<set order="0x08" stat="pAtk" val="140" />
			<set order="0x08" stat="mAtk" val="122" />
			<set order="0x08" stat="rCrit" val="4" />
			<add order="0x10" stat="accCombat" val="4.75" />
			<set order="0x08" stat="pAtkSpd" val="379" />
			<enchant val="0" order="0x0C" stat="pAtk" />
			<enchant val="0" order="0x0C" stat="mAtk" />
		</for>
	</item>
	<item id="8143" type="Weapon" nameRu="Рассеиватель Заклинаний - Магические Оковы" nameEn="Spell Breaker - Magic Hold">
		<set name="icon" val="icon.weapon_spell_breaker_i01" />
		<set name="default_action" val="equip" />
		<set name="weapon_type" val="blunt" />
		<set name="bodypart" val="rhand" />
		<set name="random_damage" val="20" />
		<set name="attack_range" val="40" />
		<set name="damage_range" val="0;0;40;120" />
		<set name="immediate_effect" val="1" />
		<set name="crystal_count" val="891" />
		<set name="crystal_type" val="b" />
		<set name="material" val="fine_steel" />
		<set name="weight" val="1620" />
		<set name="price" val="6680500" />
		<set name="soulshots" val="1" />
		<set name="spiritshots" val="1" />
		<set name="enchant_enabled" val="1" />
		<set name="is_magic_weapon" val="true" />
		<set name="onmagic_chance" val="10" />
		<set name="onmagic_skill" val="1201-25" />
		<for>
			<set order="0x08" stat="pAtk" val="140" />
			<set order="0x08" stat="mAtk" val="122" />
			<set order="0x08" stat="rCrit" val="4" />
			<add order="0x10" stat="accCombat" val="4.75" />
			<set order="0x08" stat="pAtkSpd" val="379" />
			<enchant val="0" order="0x0C" stat="pAtk" />
			<enchant val="0" order="0x0C" stat="mAtk" />
		</for>
	</item>
	<item id="8144" type="Weapon" nameRu="Кости Каим Ванула - Увеличение Маны" nameEn="Kaim Vanul's Bones - Mana Up">
		<set name="icon" val="icon.weapon_bone_of_kaim_vanul_i01" />
		<set name="default_action" val="equip" />
		<set name="weapon_type" val="blunt" />
		<set name="bodypart" val="rhand" />
		<set name="random_damage" val="20" />
		<set name="attack_range" val="40" />
		<set name="damage_range" val="0;0;40;120" />
		<set name="immediate_effect" val="1" />
		<set name="crystal_count" val="1346" />
		<set name="crystal_type" val="b" />
		<set name="material" val="bone" />
		<set name="weight" val="1570" />
		<set name="price" val="10091400" />
		<set name="soulshots" val="1" />
		<set name="spiritshots" val="1" />
		<set name="enchant_enabled" val="1" />
		<set name="is_magic_weapon" val="true" />
		<set name="item_skill" val="3014-1" />
		<for>
			<set order="0x08" stat="pAtk" val="155" />
			<set order="0x08" stat="mAtk" val="132" />
			<set order="0x08" stat="rCrit" val="4" />
			<add order="0x10" stat="accCombat" val="4.75" />
			<set order="0x08" stat="pAtkSpd" val="379" />
			<enchant val="0" order="0x0C" stat="pAtk" />
			<enchant val="0" order="0x0C" stat="mAtk" />
		</for>
	</item>
	<item id="8145" type="Weapon" nameRu="Кости Каим Ванула - Безмолвие" nameEn="Kaim Vanul's Bones - Magic Silence">
		<set name="icon" val="icon.weapon_bone_of_kaim_vanul_i01" />
		<set name="default_action" val="equip" />
		<set name="weapon_type" val="blunt" />
		<set name="bodypart" val="rhand" />
		<set name="random_damage" val="20" />
		<set name="attack_range" val="40" />
		<set name="damage_range" val="0;0;40;120" />
		<set name="immediate_effect" val="1" />
		<set name="crystal_count" val="1346" />
		<set name="crystal_type" val="b" />
		<set name="material" val="bone" />
		<set name="weight" val="1570" />
		<set name="price" val="10091400" />
		<set name="soulshots" val="1" />
		<set name="spiritshots" val="1" />
		<set name="enchant_enabled" val="1" />
		<set name="is_magic_weapon" val="true" />
		<set name="onmagic_chance" val="10" />
		<set name="onmagic_skill" val="3078-6" />
		<for>
			<set order="0x08" stat="pAtk" val="155" />
			<set order="0x08" stat="mAtk" val="132" />
			<set order="0x08" stat="rCrit" val="4" />
			<add order="0x10" stat="accCombat" val="4.75" />
			<set order="0x08" stat="pAtkSpd" val="379" />
			<enchant val="0" order="0x0C" stat="pAtk" />
			<enchant val="0" order="0x0C" stat="mAtk" />
		</for>
	</item>
	<item id="8146" type="Weapon" nameRu="Кости Каим Ванула - Конверсия" nameEn="Kaim Vanul's Bones - Conversion">
		<set name="icon" val="icon.weapon_bone_of_kaim_vanul_i01" />
		<set name="default_action" val="equip" />
		<set name="weapon_type" val="blunt" />
		<set name="bodypart" val="rhand" />
		<set name="random_damage" val="20" />
		<set name="attack_range" val="40" />
		<set name="damage_range" val="0;0;40;120" />
		<set name="immediate_effect" val="1" />
		<set name="crystal_count" val="1346" />
		<set name="crystal_type" val="b" />
		<set name="material" val="bone" />
		<set name="weight" val="1570" />
		<set name="price" val="10091400" />
		<set name="soulshots" val="1" />
		<set name="spiritshots" val="1" />
		<set name="enchant_enabled" val="1" />
		<set name="is_magic_weapon" val="true" />
		<set name="item_skill" val="3048-1" />
		<for>
			<set order="0x08" stat="pAtk" val="155" />
			<set order="0x08" stat="mAtk" val="132" />
			<set order="0x08" stat="rCrit" val="4" />
			<add order="0x10" stat="accCombat" val="4.75" />
			<set order="0x08" stat="pAtkSpd" val="379" />
			<enchant val="0" order="0x0C" stat="pAtk" />
			<enchant val="0" order="0x0C" stat="mAtk" />
		</for>
	</item>
	<item id="8147" type="Weapon" nameRu="Глаз Духа - Увеличение Маны" nameEn="Spiritual Eye - Mana Up">
		<set name="icon" val="icon.weapon_eye_of_soul_i01" />
		<set name="default_action" val="equip" />
		<set name="weapon_type" val="blunt" />
		<set name="bodypart" val="rhand" />
		<set name="random_damage" val="20" />
		<set name="attack_range" val="40" />
		<set name="damage_range" val="0;0;40;120" />
		<set name="immediate_effect" val="1" />
		<set name="crystal_count" val="1128" />
		<set name="crystal_type" val="a" />
		<set name="material" val="bone" />
		<set name="weight" val="1550" />
		<set name="price" val="14098000" />
		<set name="soulshots" val="1" />
		<set name="spiritshots" val="1" />
		<set name="enchant_enabled" val="1" />
		<set name="is_magic_weapon" val="true" />
		<set name="item_skill" val="3014-2" />
		<for>
			<set order="0x08" stat="pAtk" val="170" />
			<set order="0x08" stat="mAtk" val="143" />
			<set order="0x08" stat="rCrit" val="4" />
			<add order="0x10" stat="accCombat" val="4.75" />
			<set order="0x08" stat="pAtkSpd" val="379" />
			<enchant val="0" order="0x0C" stat="pAtk" />
			<enchant val="0" order="0x0C" stat="mAtk" />
		</for>
	</item>
	<item id="8148" type="Weapon" nameRu="Глаз Духа - Отравление" nameEn="Spiritual Eye - Magic Poison">
		<set name="icon" val="icon.weapon_eye_of_soul_i01" />
		<set name="default_action" val="equip" />
		<set name="weapon_type" val="blunt" />
		<set name="bodypart" val="rhand" />
		<set name="random_damage" val="20" />
		<set name="attack_range" val="40" />
		<set name="damage_range" val="0;0;40;120" />
		<set name="immediate_effect" val="1" />
		<set name="crystal_count" val="1128" />
		<set name="crystal_type" val="a" />
		<set name="material" val="bone" />
		<set name="weight" val="1550" />
		<set name="price" val="14098000" />
		<set name="soulshots" val="1" />
		<set name="spiritshots" val="1" />
		<set name="enchant_enabled" val="1" />
		<set name="is_magic_weapon" val="true" />
		<set name="onmagic_chance" val="8" />
		<set name="onmagic_skill" val="1168-6" />
		<set name="item_skill" val="3552-1" />
		<for>
			<set order="0x08" stat="pAtk" val="170" />
			<set order="0x08" stat="mAtk" val="143" />
			<set order="0x08" stat="rCrit" val="4" />
			<add order="0x10" stat="accCombat" val="4.75" />
			<set order="0x08" stat="pAtkSpd" val="379" />
			<enchant val="0" order="0x0C" stat="pAtk" />
			<enchant val="0" order="0x0C" stat="mAtk" />
		</for>
	</item>
	<item id="8149" type="Weapon" nameRu="Глаз Духа - Проницательность" nameEn="Spiritual Eye - Acumen">
		<set name="icon" val="icon.weapon_eye_of_soul_i01" />
		<set name="default_action" val="equip" />
		<set name="weapon_type" val="blunt" />
		<set name="bodypart" val="rhand" />
		<set name="random_damage" val="20" />
		<set name="attack_range" val="40" />
		<set name="damage_range" val="0;0;40;120" />
		<set name="immediate_effect" val="1" />
		<set name="crystal_count" val="1128" />
		<set name="crystal_type" val="a" />
		<set name="material" val="bone" />
		<set name="weight" val="1550" />
		<set name="price" val="14098000" />
		<set name="soulshots" val="1" />
		<set name="spiritshots" val="1" />
		<set name="enchant_enabled" val="1" />
		<set name="is_magic_weapon" val="true" />
		<set name="item_skill" val="3047-2" />
		<for>
			<set order="0x08" stat="pAtk" val="170" />
			<set order="0x08" stat="mAtk" val="143" />
			<set order="0x08" stat="rCrit" val="4" />
			<add order="0x10" stat="accCombat" val="4.75" />
			<set order="0x08" stat="pAtkSpd" val="379" />
			<enchant val="0" order="0x0C" stat="pAtk" />
			<enchant val="0" order="0x0C" stat="mAtk" />
		</for>
	</item>
	<item id="8150" type="Weapon" nameRu="Пылающий Череп Дракона - Проницательность" nameEn="Flaming Dragon Skull - Acumen">
		<set name="icon" val="icon.weapon_dragon_flame_head_i01" />
		<set name="default_action" val="equip" />
		<set name="weapon_type" val="blunt" />
		<set name="bodypart" val="rhand" />
		<set name="random_damage" val="20" />
		<set name="attack_range" val="40" />
		<set name="damage_range" val="0;0;40;120" />
		<set name="immediate_effect" val="1" />
		<set name="crystal_count" val="1659" />
		<set name="crystal_type" val="a" />
		<set name="material" val="fine_steel" />
		<set name="weight" val="1530" />
		<set name="price" val="20741000" />
		<set name="soulshots" val="1" />
		<set name="spiritshots" val="1" />
		<set name="enchant_enabled" val="1" />
		<set name="is_magic_weapon" val="true" />
		<set name="item_skill" val="3047-2" />
		<for>
			<set order="0x08" stat="pAtk" val="186" />
			<set order="0x08" stat="mAtk" val="152" />
			<set order="0x08" stat="rCrit" val="4" />
			<add order="0x10" stat="accCombat" val="4.75" />
			<set order="0x08" stat="pAtkSpd" val="379" />
			<enchant val="0" order="0x0C" stat="pAtk" />
			<enchant val="0" order="0x0C" stat="mAtk" />
		</for>
	</item>
	<item id="8151" type="Weapon" nameRu="Пылающий Череп Дракона - Маг. Сила" nameEn="Flaming Dragon Skull - M. Atk.">
		<set name="icon" val="icon.weapon_dragon_flame_head_i01" />
		<set name="default_action" val="equip" />
		<set name="weapon_type" val="blunt" />
		<set name="bodypart" val="rhand" />
		<set name="random_damage" val="20" />
		<set name="attack_range" val="40" />
		<set name="damage_range" val="0;0;40;120" />
		<set name="immediate_effect" val="1" />
		<set name="crystal_count" val="1659" />
		<set name="crystal_type" val="a" />
		<set name="material" val="fine_steel" />
		<set name="weight" val="1530" />
		<set name="price" val="20741000" />
		<set name="soulshots" val="1" />
		<set name="spiritshots" val="1" />
		<set name="enchant_enabled" val="1" />
		<set name="is_magic_weapon" val="true" />
		<set name="item_skill" val="3073-2" />
		<for>
			<set order="0x08" stat="pAtk" val="186" />
			<set order="0x08" stat="mAtk" val="152" />
			<set order="0x08" stat="rCrit" val="4" />
			<add order="0x10" stat="accCombat" val="4.75" />
			<set order="0x08" stat="pAtkSpd" val="379" />
			<enchant val="0" order="0x0C" stat="pAtk" />
			<enchant val="0" order="0x0C" stat="mAtk" />
		</for>
	</item>
	<item id="8152" type="Weapon" nameRu="Пылающий Череп Дракона - Безмолвие" nameEn="Flaming Dragon Skull - Magic Silence">
		<set name="icon" val="icon.weapon_dragon_flame_head_i01" />
		<set name="default_action" val="equip" />
		<set name="weapon_type" val="blunt" />
		<set name="bodypart" val="rhand" />
		<set name="random_damage" val="20" />
		<set name="attack_range" val="40" />
		<set name="damage_range" val="0;0;40;120" />
		<set name="immediate_effect" val="1" />
		<set name="crystal_count" val="1659" />
		<set name="crystal_type" val="a" />
		<set name="material" val="fine_steel" />
		<set name="weight" val="1530" />
		<set name="price" val="20741000" />
		<set name="soulshots" val="1" />
		<set name="spiritshots" val="1" />
		<set name="enchant_enabled" val="1" />
		<set name="is_magic_weapon" val="true" />
		<set name="onmagic_chance" val="10" />
		<set name="onmagic_skill" val="3074-2" />
		<set name="item_skill" val="3552-1" />
		<for>
			<set order="0x08" stat="pAtk" val="186" />
			<set order="0x08" stat="mAtk" val="152" />
			<set order="0x08" stat="rCrit" val="4" />
			<add order="0x10" stat="accCombat" val="4.75" />
			<set order="0x08" stat="pAtkSpd" val="379" />
			<enchant val="0" order="0x0C" stat="pAtk" />
			<enchant val="0" order="0x0C" stat="mAtk" />
		</for>
	</item>
	<item id="8153" type="EtcItem" nameRu="Путеводитель Путешественника" nameEn="Adventurer's Guide Book">
		<set name="icon" val="icon.etc_spell_books_blue_i00" />
		<set name="default_action" val="show_adventurer_guide_book" />
		<set name="immediate_effect" val="1" />
		<set name="material" val="paper" />
		<set name="price" val="2000" />
	</item>
	<item id="8154" type="EtcItem" nameRu="Настойка Жизни" nameEn="Herb of Life">
		<set name="immediate_effect" val="1" />
		<set name="ex_immediate_effect" val="true" />
		<set name="material" val="paper" />
		<set name="handler" val="ItemSkills" />
		<set name="item_skill" val="2244-1" />
		<set name="for_npc" val="true" />
	</item>
	<item id="8155" type="EtcItem" nameRu="Настойка Маны" nameEn="Herb of Mana">
		<set name="immediate_effect" val="1" />
		<set name="ex_immediate_effect" val="true" />
		<set name="material" val="paper" />
		<set name="handler" val="ItemSkills" />
		<set name="item_skill" val="2245-1" />
		<set name="for_npc" val="true" />
	</item>
	<item id="8156" type="EtcItem" nameRu="Настойка Силы" nameEn="Herb of Power">
		<set name="immediate_effect" val="1" />
		<set name="ex_immediate_effect" val="true" />
		<set name="material" val="paper" />
		<set name="handler" val="ItemSkills" />
		<set name="item_skill" val="2246-1" />
		<set name="for_npc" val="true" />
	</item>
	<item id="8157" type="EtcItem" nameRu="Настойка Магии" nameEn="Herb of Magic">
		<set name="immediate_effect" val="1" />
		<set name="ex_immediate_effect" val="true" />
		<set name="material" val="paper" />
		<set name="handler" val="ItemSkills" />
		<set name="item_skill" val="2247-1" />
		<set name="for_npc" val="true" />
	</item>
	<item id="8158" type="EtcItem" nameRu="Череп Мертвеца: Ранг C" nameEn="Memento Mori (C-Grade)">
		<set name="icon" val="icon.etc_raid_a_i02" />
		<set name="immediate_effect" val="1" />
		<set name="material" val="paper" />
		<set name="price" val="10000" />
		<set name="is_stackable" val="true" />
	</item>
	<item id="8159" type="EtcItem" nameRu="Череп Мертвеца: Ранг B" nameEn="Memento Mori (B-Grade)">
		<set name="icon" val="icon.etc_raid_a_i01" />
		<set name="immediate_effect" val="1" />
		<set name="material" val="paper" />
		<set name="price" val="20000" />
		<set name="is_stackable" val="true" />
	</item>
	<item id="8160" type="EtcItem" nameRu="Череп Мертвеца: Ранг A" nameEn="Memento Mori (A-Grade)">
		<set name="icon" val="icon.etc_raid_a_i00" />
		<set name="immediate_effect" val="1" />
		<set name="material" val="paper" />
		<set name="price" val="50000" />
		<set name="is_stackable" val="true" />
	</item>
	<item id="8161" type="EtcItem" nameRu="Сердце Дракона: Ранг C" nameEn="Dragon Heart (C-Grade)">
		<set name="icon" val="icon.etc_raid_b_i02" />
		<set name="immediate_effect" val="1" />
		<set name="material" val="paper" />
		<set name="price" val="10000" />
		<set name="is_stackable" val="true" />
	</item>
	<item id="8162" type="EtcItem" nameRu="Сердце Дракона: Ранг B" nameEn="Dragon Heart (B-Grade)">
		<set name="icon" val="icon.etc_raid_b_i01" />
		<set name="immediate_effect" val="1" />
		<set name="material" val="paper" />
		<set name="price" val="20000" />
		<set name="is_stackable" val="true" />
	</item>
	<item id="8163" type="EtcItem" nameRu="Сердце Дракона: Ранг A" nameEn="Dragon Heart (A-Grade)">
		<set name="icon" val="icon.etc_raid_b_i00" />
		<set name="immediate_effect" val="1" />
		<set name="material" val="paper" />
		<set name="price" val="50000" />
		<set name="is_stackable" val="true" />
	</item>
	<item id="8164" type="EtcItem" nameRu="Яйцо Земли: Ранг C" nameEn="Earth Egg (C-Grade)">
		<set name="icon" val="icon.etc_raid_c_i02" />
		<set name="immediate_effect" val="1" />
		<set name="material" val="paper" />
		<set name="price" val="10000" />
		<set name="is_stackable" val="true" />
	</item>
	<item id="8165" type="EtcItem" nameRu="Яйцо Земли: Ранг B" nameEn="Earth Egg (B-Grade)">
		<set name="icon" val="icon.etc_raid_c_i01" />
		<set name="immediate_effect" val="1" />
		<set name="material" val="paper" />
		<set name="price" val="20000" />
		<set name="is_stackable" val="true" />
	</item>
	<item id="8166" type="EtcItem" nameRu="Яйцо Земли: Ранг A" nameEn="Earth Egg (A-Grade)">
		<set name="icon" val="icon.etc_raid_c_i00" />
		<set name="immediate_effect" val="1" />
		<set name="material" val="paper" />
		<set name="price" val="50000" />
		<set name="is_stackable" val="true" />
	</item>
	<item id="8167" type="EtcItem" nameRu="Клетка Ложной Жизни: Ранг C" nameEn="Nonliving Nucleus (C-Grade)">
		<set name="icon" val="icon.etc_raid_d_i02" />
		<set name="immediate_effect" val="1" />
		<set name="material" val="paper" />
		<set name="price" val="10000" />
		<set name="is_stackable" val="true" />
	</item>
	<item id="8168" type="EtcItem" nameRu="Клетка Ложной Жизни: Ранг B" nameEn="Nonliving Nucleus (B-Grade)">
		<set name="icon" val="icon.etc_raid_d_i01" />
		<set name="immediate_effect" val="1" />
		<set name="material" val="paper" />
		<set name="price" val="20000" />
		<set name="is_stackable" val="true" />
	</item>
	<item id="8169" type="EtcItem" nameRu="Клетка Ложной Жизни: Ранг A" nameEn="Nonliving Nucleus (A-Grade)">
		<set name="icon" val="icon.etc_raid_d_i00" />
		<set name="immediate_effect" val="1" />
		<set name="material" val="paper" />
		<set name="price" val="50000" />
		<set name="is_stackable" val="true" />
	</item>
	<item id="8170" type="EtcItem" nameRu="Душа Ангела: Ранг C" nameEn="Angelic Essence (C-Grade)">
		<set name="icon" val="icon.etc_raid_e_i02" />
		<set name="immediate_effect" val="1" />
		<set name="material" val="paper" />
		<set name="price" val="10000" />
		<set name="is_stackable" val="true" />
	</item>
	<item id="8171" type="EtcItem" nameRu="Душа Ангела: Ранг B" nameEn="Angelic Essence (B-Grade)">
		<set name="icon" val="icon.etc_raid_e_i01" />
		<set name="immediate_effect" val="1" />
		<set name="material" val="paper" />
		<set name="price" val="20000" />
		<set name="is_stackable" val="true" />
	</item>
	<item id="8172" type="EtcItem" nameRu="Душа Ангела: Ранг A" nameEn="Angelic Essence (A-Grade)">
		<set name="icon" val="icon.etc_raid_e_i00" />
		<set name="immediate_effect" val="1" />
		<set name="material" val="paper" />
		<set name="price" val="50000" />
		<set name="is_stackable" val="true" />
	</item>
	<item id="8173" type="EtcItem" nameRu="Колыбель Создания: Ранг C (Не используется)" nameEn="Cradle of Creation (C-Grade) (Not In Use)">
		<set name="immediate_effect" val="1" />
		<set name="material" val="paper" />
		<set name="price" val="5000" />
		<set name="is_stackable" val="true" />
	</item>
	<item id="8174" type="EtcItem" nameRu="Колыбель Создания: Ранг B (Не используется)" nameEn="Cradle of Creation (B-Grade) (Not In Use)">
		<set name="immediate_effect" val="1" />
		<set name="material" val="paper" />
		<set name="price" val="20000" />
		<set name="is_stackable" val="true" />
	</item>
	<item id="8175" type="EtcItem" nameRu="Колыбель Создания" nameEn="Cradle of Creation">
		<set name="icon" val="icon.etc_raid_g_i00" />
		<set name="immediate_effect" val="1" />
		<set name="material" val="paper" />
		<set name="price" val="50000" />
		<set name="is_stackable" val="true" />
	</item>
	<item id="8176" type="EtcItem" nameRu="Могильная Стела Разрушения" nameEn="Destruction Tombstone">
		<set name="icon" val="icon.etc_raid_f_i00" />
		<set name="immediate_effect" val="1" />
		<set name="material" val="paper" />
		<set name="price" val="10000" />
		<set name="is_stackable" val="true" />
	</item>
	<item id="8177" type="Armor" nameRu="Диадема Участника Рейда" nameEn="Raid Challenger's Circlet">
		<set name="icon" val="icon.accessory_raid_challenger_i00" />
		<set name="default_action" val="equip" />
		<set name="bodypart" val="hair" />
		<set name="immediate_effect" val="1" />
		<set name="material" val="wood" />
		<set name="weight" val="10" />
		<set name="price" val="500000" />
	</item>
	<item id="8178" type="Armor" nameRu="Диадема Авантюриста Рейда" nameEn="Raid Adventurer's Circlet">
		<set name="icon" val="icon.accessory_raid_explorer_i00" />
		<set name="default_action" val="equip" />
		<set name="bodypart" val="hair" />
		<set name="immediate_effect" val="1" />
		<set name="material" val="wood" />
		<set name="weight" val="10" />
		<set name="price" val="500000" />
	</item>
	<item id="8179" type="Armor" nameRu="Диадема Мастера Рейда" nameEn="Raid Master's Circlet">
		<set name="icon" val="icon.accessory_raid_master_i00" />
		<set name="default_action" val="equip" />
		<set name="bodypart" val="hair" />
		<set name="immediate_effect" val="1" />
		<set name="material" val="wood" />
		<set name="weight" val="10" />
		<set name="price" val="500000" />
	</item>
	<item id="8180" type="Armor" nameRu="Диадема Ледяной Феи Сирры" nameEn="Circlet of Ice Fairy Sirra">
		<set name="icon" val="icon.accessory_ice_queen_i00" />
		<set name="default_action" val="equip" />
		<set name="bodypart" val="hair" />
		<set name="immediate_effect" val="1" />
		<set name="material" val="wood" />
		<set name="weight" val="10" />
		<set name="price" val="500000" />
	</item>
	<item id="8181" type="Armor" nameRu="Диадема Академии" nameEn="Academy Circlet">
		<set name="icon" val="icon.accessory_academy_i00" />
		<set name="default_action" val="equip" />
		<set name="bodypart" val="hair" />
		<set name="immediate_effect" val="1" />
		<set name="material" val="wood" />
		<set name="weight" val="10" />
		<set name="price" val="500000" />
		<set name="is_tradable" val="false" />
		<set name="is_dropable" val="false" />
		<set name="is_sellable" val="false" />
		<set name="equip_condition" val="{{ec_academy;1}}" />
	</item>
	<item id="8182" type="Armor" nameRu="Диадема Руны" nameEn="Circlet of Rune">
		<set name="icon" val="icon.accessory_pledge_cap1_i01" />
		<set name="default_action" val="equip" />
		<set name="bodypart" val="hair" />
		<set name="immediate_effect" val="1" />
		<set name="material" val="wood" />
		<set name="weight" val="10" />
		<set name="price" val="500000" />
		<set name="is_tradable" val="false" />
		<set name="is_dropable" val="false" />
		<set name="is_sellable" val="false" />
		<set name="item_skill" val="3633-2" />
		<set name="equip_condition" val="{{ec_castle;1};{ec_castle_num;{8}}}" />
		<cond msgId="1518">
			<and>
				<player castle="8" />
				<player pledgeClass="2" />
				<!-- Heir -->
			</and>
		</cond>
	</item>
	<item id="8183" type="Armor" nameRu="Диадема Шутгарта" nameEn="Circlet of Schuttgart">
		<set name="icon" val="icon.accessory_pledge_cap1_i07" />
		<set name="default_action" val="equip" />
		<set name="bodypart" val="hair" />
		<set name="immediate_effect" val="1" />
		<set name="material" val="wood" />
		<set name="weight" val="10" />
		<set name="price" val="500000" />
		<set name="is_tradable" val="false" />
		<set name="is_dropable" val="false" />
		<set name="is_sellable" val="false" />
		<set name="item_skill" val="3633-1" />
		<set name="equip_condition" val="{{ec_castle;1};{ec_castle_num;{9}}}" />
		<cond msgId="1518">
			<and>
				<player castle="9" />
				<player pledgeClass="2" />
				<!-- Heir -->
			</and>
		</cond>
	</item>
	<item id="8184" type="Armor" nameRu="Праздничный Колпак" nameEn="Party Hat">
		<set name="icon" val="icon.accessory_party_hat_i00" />
		<set name="default_action" val="equip" />
		<set name="bodypart" val="hairall" />
		<set name="immediate_effect" val="1" />
		<set name="material" val="wood" />
		<set name="weight" val="10" />
		<set name="price" val="2000000" />
	</item>
	<item id="8185" type="Armor" nameRu="Украшенная Перьями Шляпа" nameEn="Feathered Hat">
		<set name="icon" val="icon.accessory_archer_hat_i00" />
		<set name="default_action" val="equip" />
		<set name="bodypart" val="hairall" />
		<set name="immediate_effect" val="1" />
		<set name="material" val="wood" />
		<set name="weight" val="10" />
		<set name="price" val="2000000" />
	</item>
	<item id="8186" type="Armor" nameRu="Защитные Очки Ремесленника" nameEn="Artisan's Goggles">
		<set name="icon" val="icon.accessory_dwarf_goggle_i00" />
		<set name="default_action" val="equip" />
		<set name="bodypart" val="hairall" />
		<set name="immediate_effect" val="1" />
		<set name="material" val="wood" />
		<set name="weight" val="10" />
		<set name="price" val="2000000" />
	</item>
	<item id="8187" type="Armor" nameRu="Рога Демона" nameEn="Demon Horns">
		<set name="icon" val="icon.accessory_hair_cornu_i00" />
		<set name="default_action" val="equip" />
		<set name="bodypart" val="hair2" />
		<set name="immediate_effect" val="1" />
		<set name="material" val="wood" />
		<set name="weight" val="10" />
	</item>
	<item id="8188" type="Armor" nameRu="Крылышко Ангела" nameEn="Little Angel Wings">
		<set name="icon" val="icon.accessory_hair_ring_i00" />
		<set name="default_action" val="equip" />
		<set name="bodypart" val="hair2" />
		<set name="immediate_effect" val="1" />
		<set name="material" val="wood" />
		<set name="weight" val="10" />
		<set name="price" val="500000" />
	</item>
	<item id="8189" type="Armor" nameRu="Антенки Феи" nameEn="Fairy Antennae">
		<set name="icon" val="icon.accessory_hair_feeler_i00" />
		<set name="default_action" val="equip" />
		<set name="bodypart" val="hair2" />
		<set name="immediate_effect" val="1" />
		<set name="material" val="wood" />
		<set name="weight" val="10" />
		<set name="price" val="500000" />
	</item>
	<item id="8190" type="Weapon" nameRu="Демонический Меч Зарич" nameEn="Demonic Sword Zariche">
		<set name="icon" val="icon.weapon_unique_zariche_i00" />
		<set name="default_action" val="equip" />
		<set name="weapon_type" val="fist" />
		<set name="bodypart" val="lrhand" />
		<set name="random_damage" val="10" />
		<set name="attack_range" val="40" />
		<set name="damage_range" val="0;0;46;120" />
		<set name="immediate_effect" val="1" />
		<set name="material" val="bone" />
		<set name="weight" val="1840" />
		<set name="enchant_enabled" val="1" />
		<set name="is_tradable" val="false" />
		<set name="is_dropable" val="false" />
		<set name="is_destroyable" val="false" />
		<set name="is_sellable" val="false" />
		<set name="is_depositable" val="false" />
		<set name="item_skill" val="3603-1" />
		<for>
			<set order="0x08" stat="pAtk" val="361" />
			<set order="0x08" stat="mAtk" val="137" />
			<set order="0x08" stat="rCrit" val="8" />
			<set order="0x08" stat="pAtkSpd" val="325" />
			<enchant val="0" order="0x0C" stat="pAtk" />
			<enchant val="0" order="0x0C" stat="mAtk" />
		</for>
	</item>
	<item id="8191" type="Armor" nameRu="Ожерелье Фринтезы" nameEn="Necklace of Frintezza">
		<set name="icon" val="icon.accessory_necklace_of_frintessa_i00" />
		<set name="default_action" val="equip" />
		<set name="bodypart" val="neck" />
		<set name="immediate_effect" val="1" />
		<set name="crystal_count" val="230" />
		<set name="crystal_type" val="a" />
		<set name="material" val="gold" />
		<set name="weight" val="150" />
		<set name="price" val="3450000" />
		<set name="enchant_enabled" val="1" />
		<set name="item_skill" val="3604-1" />
		<for>
			<add order="0x10" stat="mDef" val="95" />
			<add order="0x40" stat="maxMp" val="42" />
			<enchant order="0x0C" stat="mDef" val="0" />
		</for>
	</item>
	<item id="8192" type="EtcItem" nameRu="Разрушающая Душу Стрела" nameEn="Soul Breaking Arrow">
		<set name="icon" val="icon.etc_destory_soul_arrow_i00" />
		<set name="default_action" val="skill_reduce" />
		<set name="material" val="gold" />
		<set name="weight" val="3" />
		<set name="is_dropable" val="false" />
		<set name="is_stackable" val="true" />
		<set name="handler" val="ItemSkills" />
		<set name="item_skill" val="2234-1" />
	</item>
	<item id="8193" type="EtcItem" nameRu="Зелье Рыбака - Зеленое" nameEn="Fisherman's Potion - Green">
		<set name="icon" val="icon.etc_oblivion_green_i00" />
		<set name="default_action" val="skill_reduce" />
		<set name="immediate_effect" val="1" />
		<set name="material" val="liquid" />
		<set name="weight" val="100" />
		<set name="price" val="5000" />
		<set name="is_stackable" val="true" />
		<set name="is_oly_restricted" val="true" />
		<set name="handler" val="ItemSkills" />
		<set name="item_skill" val="2274-1" />
	</item>
	<item id="8194" type="EtcItem" nameRu="Зелье Рыбака - Нефритовое" nameEn="Fisherman's Potion - Jade">
		<set name="icon" val="icon.etc_oblivion_jade_i00" />
		<set name="default_action" val="skill_reduce" />
		<set name="immediate_effect" val="1" />
		<set name="material" val="liquid" />
		<set name="weight" val="100" />
		<set name="price" val="5000" />
		<set name="is_stackable" val="true" />
		<set name="is_oly_restricted" val="true" />
		<set name="handler" val="ItemSkills" />
		<set name="item_skill" val="2274-2" />
	</item>
	<item id="8195" type="EtcItem" nameRu="Зелье Рыбака - Синее" nameEn="Fisherman's Potion - Blue">
		<set name="icon" val="icon.etc_oblivion_blue_i00" />
		<set name="default_action" val="skill_reduce" />
		<set name="immediate_effect" val="1" />
		<set name="material" val="liquid" />
		<set name="weight" val="100" />
		<set name="price" val="5000" />
		<set name="is_stackable" val="true" />
		<set name="is_oly_restricted" val="true" />
		<set name="handler" val="ItemSkills" />
		<set name="item_skill" val="2274-3" />
	</item>
	<item id="8196" type="EtcItem" nameRu="Зелье Рыбака - Желтое" nameEn="Fisherman's Potion - Yellow">
		<set name="icon" val="icon.etc_oblivion_yellow_i00" />
		<set name="default_action" val="skill_reduce" />
		<set name="immediate_effect" val="1" />
		<set name="material" val="liquid" />
		<set name="weight" val="100" />
		<set name="price" val="5000" />
		<set name="is_stackable" val="true" />
		<set name="is_oly_restricted" val="true" />
		<set name="handler" val="ItemSkills" />
		<set name="item_skill" val="2274-4" />
	</item>
	<item id="8197" type="EtcItem" nameRu="Зелье Рыбака - Оранжевое" nameEn="Fisherman's Potion - Orange">
		<set name="icon" val="icon.etc_oblivion_orange_i00" />
		<set name="default_action" val="skill_reduce" />
		<set name="immediate_effect" val="1" />
		<set name="material" val="liquid" />
		<set name="weight" val="100" />
		<set name="price" val="5000" />
		<set name="is_stackable" val="true" />
		<set name="is_oly_restricted" val="true" />
		<set name="handler" val="ItemSkills" />
		<set name="item_skill" val="2274-5" />
	</item>
	<item id="8198" type="EtcItem" nameRu="Зелье Рыбака - Фиолетовое" nameEn="Fisherman's Potion - Purple">
		<set name="icon" val="icon.etc_oblivion_violet_i00" />
		<set name="default_action" val="skill_reduce" />
		<set name="immediate_effect" val="1" />
		<set name="material" val="liquid" />
		<set name="weight" val="100" />
		<set name="price" val="5000" />
		<set name="is_stackable" val="true" />
		<set name="is_oly_restricted" val="true" />
		<set name="handler" val="ItemSkills" />
		<set name="item_skill" val="2274-6" />
	</item>
	<item id="8199" type="EtcItem" nameRu="Зелье Рыбака - Красное" nameEn="Fisherman's Potion - Red">
		<set name="icon" val="icon.etc_oblivion_red_i00" />
		<set name="default_action" val="skill_reduce" />
		<set name="immediate_effect" val="1" />
		<set name="material" val="liquid" />
		<set name="weight" val="100" />
		<set name="price" val="5000" />
		<set name="is_stackable" val="true" />
		<set name="is_oly_restricted" val="true" />
		<set name="handler" val="ItemSkills" />
		<set name="item_skill" val="2274-7" />
	</item>
</list>