<?xml version="1.0" encoding="UTF-8"?>
<list xmlns:ns0="http://www.w3.org/2001/XMLSchema-instance" ns0:noNamespaceSchemaLocation="multisell.xsd">
	<!-- Pets	-->
	
	<item>
   <!-- Adena -->
		<ingredient count="100" id="26641" />
   <production id="2375" count="1"/>
  </item>
  
	<item>
   <!-- Adena -->
		<ingredient count="150" id="26641" />
   <production id="6650" count="1"/>
  </item>
  
	<item>
   <!-- Adena -->
		<ingredient count="150" id="26641" />
   <production id="6649" count="1"/>
  </item>
  
	<item>
   <!-- Adena -->
		<ingredient count="150" id="26641" />
   <production id="6648" count="1"/>
  </item>
  
	<item>
   <!-- Adena -->
		<ingredient count="150" id="26641" />
   <production id="4038" count="1"/>
  </item>
</list>
